setup.py
pillow_retry/__init__.py
pillow_retry/models.py
pillow_retry/tasks.py
pillow_retry/tests.py
pillow_retry/migrations/0001_initial.py
pillow_retry/migrations/0002_pillowerror_queued.py
pillow_retry/migrations/0003_auto_20151002_0944.py
pillow_retry/migrations/__init__.py
pillow_retry/south_migrations/0001_initial.py
pillow_retry/south_migrations/0002_auto.py
pillow_retry/south_migrations/0003_add_unique_doc_id_pillow.py
pillow_retry/south_migrations/0004_del_field_error_message.py
pillow_retry/south_migrations/0005_add_field_change_dict.py
pillow_retry/south_migrations/006_add_doc_meta.py
pillow_retry/south_migrations/007_remove_like_indexes.py
pillow_retry/south_migrations/__init__.py
pillowtop/__init__.py
pillowtop/const.py
pillowtop/couchdb.py
pillowtop/exceptions.py
pillowtop/listener.py
pillowtop/logger.py
pillowtop/models.py
pillowtop/run_pillowtop.py
pillowtop/utils.py
pillowtop.egg-info/PKG-INFO
pillowtop.egg-info/SOURCES.txt
pillowtop.egg-info/dependency_links.txt
pillowtop.egg-info/requires.txt
pillowtop.egg-info/top_level.txt
pillowtop/checkpoints/__init__.py
pillowtop/checkpoints/manager.py
pillowtop/checkpoints/util.py
pillowtop/dao/__init__.py
pillowtop/dao/couch.py
pillowtop/dao/exceptions.py
pillowtop/dao/interface.py
pillowtop/dao/mock.py
pillowtop/feed/__init__.py
pillowtop/feed/couch.py
pillowtop/feed/interface.py
pillowtop/feed/mock.py
pillowtop/management/__init__.py
pillowtop/management/pillowstate.py
pillowtop/management/commands/__init__.py
pillowtop/management/commands/ptop_es_manage.py
pillowtop/management/commands/ptop_reset_checkpoint.py
pillowtop/management/commands/ptop_run_docs.py
pillowtop/management/commands/run_ptop.py
pillowtop/pillow/__init__.py
pillowtop/pillow/interface.py
pillowtop/tests/__init__.py
pillowtop/tests/test_changes.py
pillowtop/tests/test_checkpoints.py
pillowtop/tests/test_config.py
pillowtop/tests/test_couch.py
pillowtop/tests/test_dao.py
pillowtop/tests/test_elasticsearch.py
pillowtop/tests/test_import_pillows.py
pillowtop/tests/utils.py