Metadata-Version: 1.0
Name: pillowtop
Version: 0.1.8
Summary: A couchdbkit changes listener for doing backend processing
Home-page: http://www.dimagi.com/
Author: Dimagi
Author-email: dev@dimagi.com
License: UNKNOWN
Platform: UNKNOWN
